setup.py
SmartAPI/__init__.py
SmartAPI.egg-info/PKG-INFO
SmartAPI.egg-info/SOURCES.txt
SmartAPI.egg-info/dependency_links.txt
SmartAPI.egg-info/requires.txt
SmartAPI.egg-info/top_level.txt
SmartAPI/agents/Agent.py
SmartAPI/agents/EventAgent.py
SmartAPI/agents/RegistrationAgent.py
SmartAPI/agents/RegistrySearchAgent.py
SmartAPI/agents/SearchAgent.py
SmartAPI/agents/SharingAgent.py
SmartAPI/agents/TransactionAgent.py
SmartAPI/agents/__init__.py
SmartAPI/common/Auth.py
SmartAPI/common/CONTENTTYPES.py
SmartAPI/common/COUNTRY.py
SmartAPI/common/ClassMapper.py
SmartAPI/common/ConceptDetails.py
SmartAPI/common/CryptoKeyWallet.py
SmartAPI/common/DATATYPE.py
SmartAPI/common/HttpClient.py
SmartAPI/common/HttpMessage.py
SmartAPI/common/NS.py
SmartAPI/common/PROPERTY.py
SmartAPI/common/RESOURCE.py
SmartAPI/common/SERIALIZATION.py
SmartAPI/common/SmartAPICrypto.py
SmartAPI/common/Tools.py
SmartAPI/common/URLs.py
SmartAPI/common/VARIANT.py
SmartAPI/common/ValidationMode.py
SmartAPI/common/__init__.py
SmartAPI/factory/CommandFactory.py
SmartAPI/factory/Factory.py
SmartAPI/factory/NotificationFactory.py
SmartAPI/factory/RequestFactory.py
SmartAPI/factory/ResponseFactory.py
SmartAPI/factory/__init__.py
SmartAPI/model/Ability.py
SmartAPI/model/AbstractEntity.py
SmartAPI/model/Activity.py
SmartAPI/model/Address.py
SmartAPI/model/AliveRequest.py
SmartAPI/model/AliveResponse.py
SmartAPI/model/Availability.py
SmartAPI/model/Capacity.py
SmartAPI/model/Condition.py
SmartAPI/model/Controllability.py
SmartAPI/model/Coordinates.py
SmartAPI/model/Device.py
SmartAPI/model/Direction.py
SmartAPI/model/Entity.py
SmartAPI/model/Enumeration.py
SmartAPI/model/Error.py
SmartAPI/model/Evaluation.py
SmartAPI/model/GrObj.py
SmartAPI/model/Input.py
SmartAPI/model/InterfaceAddress.py
SmartAPI/model/Map.py
SmartAPI/model/Message.py
SmartAPI/model/Notification.py
SmartAPI/model/Obj.py
SmartAPI/model/Offering.py
SmartAPI/model/Organization.py
SmartAPI/model/Orientation.py
SmartAPI/model/Output.py
SmartAPI/model/Parameter.py
SmartAPI/model/Person.py
SmartAPI/model/PhysicalEntity.py
SmartAPI/model/PriceSpecification.py
SmartAPI/model/Provenance.py
