Metadata-Version: 1.1
Name: SmartAPI
Version: 1.1.0
Summary: Smart API RDF model manipulation in Python
Home-page: http://www.smart-api.io
Author: Asema Electronics Ltd
Author-email: python_dev@asema.com
License: BSD
Platform: UNKNOWN
Classifier: Development Status :: 4 - Beta
Classifier: Intended Audience :: Developers
Classifier: Operating System :: OS Independent
Classifier: Programming Language :: Python :: 2
